Metadata-Version: 2.1
Name: nuevo
Version: 0.0.1
Summary: Simple python library for creating neural networks
Author: Lucas Czerny
Author-email: czernylucas@gmail.com
License: MIT
Platform: UNKNOWN
Classifier: Programming Language :: Python :: 3
Classifier: Programming Language :: Python :: 3.10
Classifier: License :: OSI Approved :: MIT License
Classifier: Operating System :: OS Independent
License-File: LICENSE.txt
